datamodelsFrontier/__init__.py
datamodelsFrontier/downstream.py
datamodelsFrontier/external.py
datamodelsFrontier-1.2.5.dist-info/LICENSE.txt
datamodelsFrontier-1.2.5.dist-info/METADATA
datamodelsFrontier-1.2.5.dist-info/WHEEL
datamodelsFrontier-1.2.5.dist-info/top_level.txt
datamodelsFrontier-1.2.5.dist-info/RECORD
