Metadata-Version: 2.1
Name: datamodelsFrontier
Version: 1.2.5
Summary: Datamodels needed for Frontier API
Home-page: UNKNOWN
Author: THG-Frontier
Author-email: DL-TechAPIGateway@thehutgroup.com
License: UNKNOWN
Platform: UNKNOWN
Classifier: Programming Language :: Python :: 3
Classifier: Programming Language :: Python :: 3.6
Classifier: Programming Language :: Python :: 3.7
License-File: LICENSE.txt
Requires-Dist: pydantic
Provides-Extra: dev
Requires-Dist: pytest (>=4) ; extra == 'dev'
Requires-Dist: pytest-cov (>=2) ; extra == 'dev'
